Workbook

Sheet 1. Premissas
A1: MODELO DE VIABILIDADE — INCORPORADORA IMOBILIÁRIA
A2: PREMISSAS DO EMPREENDIMENTO — Empreendimento Piloto (Ano 1)
A3: Legenda: Azul = entrada manual | Preto = fórmula calculada | C3: Versão 1.0 — Março/2026
A5: A — PRODUTO E MERCADO
A6: Premissa | B6: Valor | C6: Observação
A7: Número de unidades | B7: 16 | C7: Apartamentos ou casas no empreendimento
A8: Área privativa média (m²) | B8: 65 | C8: m² por unidade — área util
A9: Área total construída (m²) | B9: =B7*B8 | C9: =B8*B9
A10: Preço de venda por m² (R$) | B10: 5500 | C10: Benchmark: R$ 4.500–R$ 7.000 conforme padrão/local
A11: VGV Total (R$) | B11: =B7*B8*B10 | C11: =B8*B9*B11
A12: Padrão do empreendimento | B12: Médio | C12: Simples / Médio / Alto
A14: B — ESTRUTURA DE CUSTOS
A15: Item de Custo | B15: % sobre VGV | C15: R$ Estimado
A16: Terreno (compra ou permuta física) | B16: 0.18 | C16: =B16*B11 | D16: Benchmark: 15–22% do VGV
A17: Custo de Construção (CUB + BDI) | B17: 0.45 | C17: =B17*B11 | D17: Benchmark: 40–55% do VGV
A18: Projetos e Aprovações | B18: 0.03 | C18: =B18*B11 | D18: Arquitetura, Engenharia, Despachante, CRI
A19: Marketing e Vendas (comissão + campanha) | B19: 0.06 | C19: =B19*B11 | D19: Comissão corretores: 4–6% VGV
A20: Administração / Taxa de Incorporação | B20: 0.05 | C20: =B20*B11 | D20: Holding cobra 5–8% VGV como fee de gestão
A21: Impostos RET (% sobre receita) | B21: 0.04 | C21: =B21*B11 | D21: RET: 4% sobre receita bruta com Patrimônio de Afetação
A22: Contingência | B22: 0.03 | C22: =B22*B11 | D22: Reserva para imprevistos de obra e prazo
A23: CUSTO TOTAL | B23: =SUM(B16:B22) | C23: =SUM(C16:C22)
A25: C — RESULTADO E RETORNO
A26: Indicador | B26: Valor | C26: Benchmark de Mercado
A27: VGV Total | B27: =B11 | C27: 100% do VGV
A28: (-) Custo Total | B28: =C23 | C28: Soma de todos os custos acima
A29: Lucro Bruto do Empreendimento | B29: =B27-B28 | C29: VGV - Custo Total
A30: Margem Bruta sobre VGV | B30: =B29/B11 | C30: Benchmark saudável: ≥ 25%
A31: Capital Próprio Estimado (entrada + gap) | B31: 800000 | C31: ⚠ Ajuste conforme capital disponível real
A32: ROE (Retorno sobre Capital Próprio) | B32: =B29/B31 | C32: Benchmark: ≥ 25% total do projeto
A33: Prazo estimado do empreendimento (meses) | B33: 30 | C33: Da compra do terreno até última entrega
A34: TIR Anualizada (estimativa simplificada) | B34: =((1+B31)^(12/B33))-1 | C34: Estimativa! Use fluxo de caixa para TIR real.
A36: D — ESTRUTURA DE CAPTAÇÃO
A37: Fonte de Recurso | B37: % do Custo Total | C37: R$ Estimado
A38: Capital Próprio (sócios) | B38: 0.25 | C38: =B38*C23 | D38: Terreno + pré-obra + contrapartida CEF
A39: Financiamento CEF (produção) | B39: 0.55 | C39: =B39*C23 | D39: Até 80% do custo de obra aprovado
A40: Permuta / Consórcio | B40: 0.15 | C40: =B40*C23 | D40: Terreno via permuta ou crédito contemplado
A41: Outros / Investidor externo | B41: 0.05 | C41: =B41*C23 | D41: Se necessário — via SPE ou contrato específico
A42: TOTAL CAPTAÇÃO | B42: =SUM(B38:B41) | C42: =SUM(C38:C41)

Sheet 2. Fluxo de Caixa
A1: FLUXO DE CAIXA SIMPLIFICADO — EMPREENDIMENTO PILOTO
A2: Premissas dinâmicas: ajuste os % de vendas e custos mensais conforme cronograma real
A4: Item | B4: Pré-obra | E4: Obra | K4: Entrega/Pós
A5: Mês | B5: Mês 01 | C5: Mês 02 | D5: Mês 03 | E5: Mês 04 | F5: Mês 05 | G5: Mês 06 | H5: Mês 07 | I5: Mês 08 | J5: Mês 09 | K5: Mês 10 | L5: Mês 11 | M5: Mês 12 | N5: TOTAL
A6: RECEITAS
A7: Receita de Vendas (% VGV por mês) | B7: =0.0*'1. Premissas'!B11 | C7: =0.05*'1. Premissas'!B11 | D7: =0.1*'1. Premissas'!B11 | E7: =0.08*'1. Premissas'!B11 | F7: =0.08*'1. Premissas'!B11 | G7: =0.08*'1. Premissas'!B11 | H7: =0.08*'1. Premissas'!B11 | I7: =0.08*'1. Premissas'!B11 | J7: =0.07*'1. Premissas'!B11 | K7: =0.1*'1. Premissas'!B11 | L7: =0.1*'1. Premissas'!B11 | M7: =0.18*'1. Premissas'!B11 | N7: =SUM(B7:M7)
A8: Liberações Financiamento CEF | B8: =0.0*'1. Premissas'!C23 | C8: =0.0*'1. Premissas'!C23 | D8: =0.0*'1. Premissas'!C23 | E8: =0.12*'1. Premissas'!C23 | F8: =0.12*'1. Premissas'!C23 | G8: =0.12*'1. Premissas'!C23 | H8: =0.12*'1. Premissas'!C23 | I8: =0.1*'1. Premissas'!C23 | J8: =0.1*'1. Premissas'!C23 | K8: =0.1*'1. Premissas'!C23 | L8: =0.1*'1. Premissas'!C23 | M8: =0.12*'1. Premissas'!C23 | N8: =SUM(B8:M8)
A9: TOTAL ENTRADAS | B9: =B7+B8 | C9: =C7+C8 | D9: =D7+D8 | E9: =E7+E8 | F9: =F7+F8 | G9: =G7+G8 | H9: =H7+H8 | I9: =I7+I8 | ... M9: =M7+M8 | N9: =SUM(B9:M9)
A11: SAÍDAS (CUSTOS)
A12: Terreno / Permuta | B12: =0.8*'1. Premissas'!C23 | C12: =0.2*'1. Premissas'!C23 | D12: =0.0*'1. Premissas'!C23 | E12: =0.0*'1. Premissas'!C23 | F12: =0.0*'1. Premissas'!C23 | G12: =0.0*'1. Premissas'!C23 | H12: =0.0*'1. Premissas'!C23 | I12: =0.0*'1. Premissas'!C23 | J12: =0.0*'1. Premissas'!C23 | K12: =0.0*'1. Premissas'!C23 | L12: =0.0*'1. Premissas'!C23 | M12: =0.0*'1. Premissas'!C23 | N12: =SUM(B12:M12)
A13: Projetos e Aprovações | B13: =0.3*'1. Premissas'!C23 | C13: =0.3*'1. Premissas'!C23 | D13: =0.3*'1. Premissas'!C23 | E13: =0.1*'1. Premissas'!C23 | F13: =0.0*'1. Premissas'!C23 | G13: =0.0*'1. Premissas'!C23 | H13: =0.0*'1. Premissas'!C23 | I13: =0.0*'1. Premissas'!C23 | J13: =0.0*'1. Premissas'!C23 | K13: =0.0*'1. Premissas'!C23 | L13: =0.0*'1. Premissas'!C23 | M13: =0.0*'1. Premissas'!C23 | N13: =SUM(B13:M13)
A14: Custo de Obra (execução) | B14: =0.0*'1. Premissas'!C23 | C14: =0.0*'1. Premissas'!C23 | D14: =0.02*'1. Premissas'!C23 | E14: =0.1*'1. Premissas'!C23 | F14: =0.12*'1. Premissas'!C23 | G14: =0.14*'1. Premissas'!C23 | H14: =0.14*'1. Premissas'!C23 | I14: =0.14*'1. Premissas'!C23 | J14: =0.14*'1. Premissas'!C23 | K14: =0.12*'1. Premissas'!C23 | L14: =0.06*'1. Premissas'!C23 | M14: =0.02*'1. Premissas'!C23 | N14: =SUM(B14:M14)
A15: Marketing e Vendas | B15: =0.05*'1. Premissas'!C23 | C15: =0.1*'1. Premissas'!C23 | D15: =0.1*'1. Premissas'!C23 | E15: =0.1*'1. Premissas'!C23 | F15: =0.08*'1. Premissas'!C23 | G15: =0.08*'1. Premissas'!C23 | H15: =0.08*'1. Premissas'!C23 | I15: =0.08*'1. Premissas'!C23 | J15: =0.08*'1. Premissas'!C23 | K15: =0.08*'1. Premissas'!C23 | L15: =0.09*'1. Premissas'!C23 | M15: =0.08*'1. Premissas'!C23 | N15: =SUM(B15:M15)
A16: Impostos RET (4% s/ receita) | B16: =0.04*B7 | C16: =0.04*C7 | D16: =0.04*D7 | E16: =0.04*E7 | F16: =0.04*F7 | G16: =0.04*G7 | H16: =0.04*H7 | I16: =0.04*I7 | ... M16: =0.04*M7 | N16: =SUM(B16:M16)
A17: Despesas Administrativas / Fee Holding | B17: =0.08*'1. Premissas'!C23 | C17: =0.08*'1. Premissas'!C23 | D17: =0.08*'1. Premissas'!C23 | E17: =0.08*'1. Premissas'!C23 | F17: =0.08*'1. Premissas'!C23 | G17: =0.08*'1. Premissas'!C23 | H17: =0.08*'1. Premissas'!C23 | I17: =0.08*'1. Premissas'!C23 | J17: =0.08*'1. Premissas'!C23 | K17: =0.09*'1. Premissas'!C23 | L17: =0.09*'1. Premissas'!C23 | M17: =0.1*'1. Premissas'!C23 | N17: =SUM(B17:M17)
A18: TOTAL SAÍDAS | B18: =SUM(B12:B17) | C18: =SUM(C12:C17) | D18: =SUM(D12:D17) | E18: =SUM(E12:E17) | F18: =SUM(F12:F17) | G18: =SUM(G12:G17) | H18: =SUM(H12:H17) | I18: =SUM(I12:I17) | ... M18: =SUM(M12:M17) | N18: =SUM(B18:M18)
A20: RESULTADO
A21: Saldo Mensal (Entradas - Saídas) | B21: =B9-B18 | C21: =C9-C18 | D21: =D9-D18 | E21: =E9-E18 | F21: =F9-F18 | G21: =G9-G18 | H21: =H9-H18 | I21: =I9-I18 | ... M21: =M9-M18 | N21: =SUM(B21:M21)
A22: Saldo Acumulado | B22: =B21 | C22: =B22+C21 | D22: =C22+D21 | E22: =D22+E21 | F22: =E22+F21 | G22: =F22+G21 | H22: =G22+H21 | I22: =H22+I21 | J22: =I22+J21 | ... M22: =L22+M21 | N22: Ver saldo acum. →

Sheet 3. Sensibilidade
A1: ANÁLISE DE SENSIBILIDADE — MARGEM vs. CUSTO DE OBRA e PREÇO/m²
A2: Impacto na Margem Bruta conforme variação do Custo de Construção e Preço de Venda/m²
A4: VARIAÇÃO DO CUSTO DE OBRA (% VGV)
A5: Custo Obra % VGV ↓ / Preço/m² → | B5: Preço -19% | C5: Preço -9% | D5: Preço +0% | E5: Preço +10% | F5: Preço +19%
A6: Obra = 40% VGV | B6: 0.112 | C6: 0.167 | D6: 0.21 | E6: 0.245 | F6: 0.275
A7: Obra = 45% VGV | B7: 0.063 | C7: 0.117 | D7: 0.16 | E7: 0.195 | F7: 0.225
A8: Obra = 50% VGV | B8: 0.013 | C8: 0.067 | D8: 0.11 | E8: 0.145 | F8: 0.175
A9: Obra = 55% VGV | B9: -0.038 | C9: 0.017 | D9: 0.06 | E9: 0.095 | F9: 0.125
A10: Obra = 60% VGV | B10: -0.087 | C10: -0.033 | D10: 0.01 | E10: 0.045 | F10: 0.075
A12: Verde ≥ 28% (meta) | Amarelo 20–28% (atenção) | Vermelho < 20% (inviável)
A14: ANÁLISE DE RETORNO — CAPITAL PRÓPRIO vs. PRAZO
A15: Prazo do Projeto ↓ / Lucro Total → | B15: Lucro R$ 500k | C15: Lucro R$ 750k | D15: Lucro R$ 1000k | E15: Lucro R$ 1500k | F15: Lucro R$ 2000k
A16: 18 meses | B16: 0.382 | C16: 0.554 | D16: 0.717 | E16: 1.022 | F16: 1.305
A17: 24 meses | B17: 0.275 | C17: 0.392 | D17: 0.5 | E17: 0.696 | F17: 0.871
A18: 30 meses | B18: 0.214 | C18: 0.303 | D18: 0.383 | E18: 0.526 | F18: 0.651
A19: 36 meses | B19: 0.176 | C19: 0.247 | D19: 0.31 | E19: 0.422 | F19: 0.518
A20: 48 meses | B20: 0.129 | C20: 0.18 | D20: 0.225 | E20: 0.302 | F20: 0.368
A22: Capital próprio base: R$ 800k | Verde ≥ 18% a.a. | Amarelo 12–18% | Vermelho < 12%

Sheet 4. Análise de Terrenos
A1: SCORECARD DE ANÁLISE DE TERRENOS
A2: Compare até 3 terrenos simultaneamente. Azul = entrada manual.
A4: Critério de Análise | B4: Terreno A | C4: Terreno B | D4: Terreno C | E4: Peso (%) | F4: Observação
A5: Localização e acesso | B5: Nota 1–10 | C5: Nota 1–10 | D5: Nota 1–10 | E5: 20% | F5: Infraestrutura, transporte, valorização
A6: Zoneamento / Aproveitamento | B6: Nota 1–10 | C6: Nota 1–10 | D6: Nota 1–10 | E6: 20% | F6: Coeficiente de aproveitamento, testada, recuos
A7: Preço do terreno (% VGV estimado) | B7: Nota 1–10 | C7: Nota 1–10 | D7: Nota 1–10 | E7: 20% | F7: Quanto menor o % VGV, melhor a nota
A8: Situação jurídica / Due Diligence | B8: Nota 1–10 | C8: Nota 1–10 | D8: Nota 1–10 | E8: 15% | F8: Escritura, ITBI pago, dívidas, ônus
A9: Demanda local (pesquisa) | B9: Nota 1–10 | C9: Nota 1–10 | D9: Nota 1–10 | E9: 15% | F9: Absorção mensal, concorrentes ativos
A10: Viabilidade de permuta (facilidade) | B10: Nota 1–10 | C10: Nota 1–10 | D10: Nota 1–10 | E10: 10% | F10: Abertura do proprietário, histórico
A11: SCORE TOTAL PONDERADO (preenchimento manual) | B11: --- | C11: --- | D11: ---
A13: DADOS FINANCEIROS DO TERRENO SELECIONADO
A14: Endereço / Identificação | B14: Rua/Bairro — Cidade/UF
A15: Área do terreno (m²) | B15: 500
A16: Preço pedido pelo proprietário (R$) | B16: 900000
A17: Preço negociado estimado (R$) | B17: 800000
A18: % do VGV estimado | B18: =D/VGV — calcular manualmente
A19: Modalidade de aquisição | B19: Compra direta / Permuta / Consórcio
A20: Potencial construtivo (unidades) | B20: 16
A21: VGV estimado do terreno | B21: =unidades × área média × R$/m²
A22: Contato do proprietário | B22: Nome / Telefone
A23: Status da negociação | B23: Prospecção / Em negociação / Fechado

Sheet 5. KPIs e Metas
A1: PAINEL DE KPIs — INCORPORADORA IMOBILIÁRIA
A3: KPIs FINANCEIROS POR EMPREENDIMENTO
A4: KPI | B4: Unidade | C4: Meta | D4: Realizado | E4: Observação
A5: VGV Total do Empreendimento | B5: R$ | C5: Benchmark | D5: Real | E5: Quanto maior o projeto, maior a escala
A6: Margem Bruta sobre VGV | B6: % | C6: ≥ 25% | D6: --- | E6: Abaixo de 20% = rever premissas
A7: ROE (Retorno s/ Capital Próprio) | B7: % | C7: ≥ 25% | D7: --- | E7: Retorno total do projeto
A8: TIR Anualizada | B8: % a.a. | C8: ≥ 18% | D8: --- | E8: Considera prazo total do projeto
A9: Payback do Capital Próprio | B9: meses | C9: ≤ 36 | D9: --- | E9: Meses até recuperar o investido
A10: Custo de Obra / VGV | B10: % | C10: ≤ 55% | D10: --- | E10: Inclui materiais, mão de obra, BDI
A12: KPIs COMERCIAIS
A13: KPI | B13: Unidade | C13: Meta | D13: Realizado | E13: Observação
A14: % Vendas no lançamento (30 dias) | B14: % | C14: ≥ 40% | D14: --- | E14: Válida a aceitação do produto
A15: % Vendas antes do início da obra | B15: % | C15: ≥ 60% | D15: --- | E15: Gatilho para financiamento CEF
A16: Velocidade de Vendas (un/mês) | B16: un/mês | C16: Definir | D16: --- | E16: Depende do total de unidades
A17: Ticket médio realizado vs. planejado | B17: % | C17: ≥ 100% | D17: --- | E17: Indica pricing adequado
A18: % Unidades com financiamento bancário | B18: % | C18: Benchmark | D18: --- | E18: Indica perfil dos compradores
A20: KPIs OPERACIONAIS DE OBRA
A21: KPI | B21: Unidade | C21: Meta | D21: Realizado | E21: Observação
A22: Desvio de prazo de obra | B22: % | C22: ≤ 10% | D22: --- | E22: Atraso impacta custo e reputação
A23: Desvio de custo de obra | B23: % | C23: ≤ 8% | D23: --- | E23: Orçado vs. realizado
A24: % Medições pagas no prazo pela CEF | B24: % | C24: =100% | D24: --- | E24: Indica conformidade do laudo
A25: Prazo de aprovação na prefeitura | B25: dias | C25: ≤ 180 | D25: --- | E25: Contado do protocolo ao alvará
A26: Número de notificações/embargos | B26: qtd | C26: =0 | D26: --- | E26: Risco jurídico e reputacional
